django_field_logger-0.1.1.dist-info/licenses/LICENSE
fieldlogger/__init__.py
fieldlogger/apps.py
fieldlogger/config.py
fieldlogger/encoding.py
fieldlogger/fieldlogger.py
fieldlogger/managers.py
fieldlogger/mixins.py
fieldlogger/models.py
fieldlogger/signals.py
fieldlogger/utils.py
fieldlogger/migrations/0001_initial.py
fieldlogger/migrations/__init__.py
django_field_logger-0.1.1.dist-info/METADATA
django_field_logger-0.1.1.dist-info/WHEEL
django_field_logger-0.1.1.dist-info/top_level.txt
django_field_logger-0.1.1.dist-info/RECORD
