Metadata-Version: 2.4
Name: django-field-logger
Version: 0.1.1
Summary: A Django app for logging changes in model fields.
Home-page: https://github.com/nibblex/django-field-logger
Author: Sergio Rodríguez
Author-email: srodriguez3441@gmail.com
Maintainer: Sergio Rodríguez
Maintainer-email: srodriguez3441@gmail.com
License: MIT
Classifier: Framework :: Django
Classifier: Framework :: Django :: 3.1
Classifier: Framework :: Django :: 3.2
Classifier: Framework :: Django :: 4.0
Classifier: Framework :: Django :: 4.1
Classifier: Framework :: Django :: 4.2
Classifier: Framework :: Django :: 5.0
Classifier: Intended Audience :: Developers
Classifier: Operating System :: OS Independent
Classifier: Programming Language :: Python :: 3
Classifier: Programming Language :: Python :: 3.8
Classifier: Programming Language :: Python :: 3.9
Classifier: Programming Language :: Python :: 3.10
Classifier: Programming Language :: Python :: 3.11
Classifier: Programming Language :: Python :: 3.12
Classifier: Programming Language :: Python :: 3.13
Classifier: Topic :: Software Development :: Libraries :: Python Modules
Requires-Python: >=3.8
License-File: LICENSE
Requires-Dist: Django>=3.1
Dynamic: license-file
